python_orders/__init__.py
python_orders/adapters/__init__.py
python_orders/adapters/db/__init__.py
python_orders/adapters/db/json/__init__.py
python_orders/adapters/db/json/config.py
python_orders/adapters/db/json/orders/__init__.py
python_orders/adapters/db/json/orders/repository.py
python_orders/application/__init__.py
python_orders/application/common/__init__.py
python_orders/application/common/interfaces/__init__.py
python_orders/application/common/interfaces/orders.py
python_orders/application/common/use_case.py
python_orders/application/get_orders/__init__.py
python_orders/application/get_orders/interfaces.py
python_orders/application/get_orders/use_case.py
python_orders/application/save_order/__init__.py
python_orders/application/save_order/dto.py
python_orders/application/save_order/interfaces.py
python_orders/application/save_order/use_case.py
python_orders/client.py
python_orders/domain/__init__.py
python_orders/domain/dto/__init__.py
python_orders/domain/dto/order.py
python_orders/domain/models/__init__.py
python_orders/domain/models/email.py
python_orders/domain/models/order.py
python_orders/domain/services/__init__.py
python_orders/domain/services/order.py
python_orders/domain/value_objects/__init__.py
python_orders/domain/value_objects/order_item.py
python_orders/main/__init__.py
python_orders/main/desktop.py
python_orders/main/di_builder.py
python_orders/main/settings.py
python_orders/main/socket_server.py
python_orders/presentation/__init__.py
python_orders/presentation/qt/__init__.py
python_orders/presentation/qt/win_to_show_items.py
python_orders/presentation/qt/window_to_show_items.py
python_orders/presentation/socket/__init__.py
python_orders/presentation/socket/config.py
python_orders/presentation/socket/dto.py
python_orders/presentation/socket/server.py
python_orders/server.py
python_orders_examm-0.1.0.dist-info/METADATA
python_orders_examm-0.1.0.dist-info/WHEEL
python_orders_examm-0.1.0.dist-info/RECORD
