Metadata-Version: 2.1
Name: python-orders-examm
Version: 0.1.0
Summary: abc
Author: lLotosl
Author-email: lotosyt1@gmail.com
Requires-Python: >=3.5,<4.0
Classifier: License :: OSI Approved :: MIT License
Classifier: Operating System :: OS Independent
Classifier: Programming Language :: Python :: 3
Classifier: Programming Language :: Python :: 3.5
Classifier: Programming Language :: Python :: 3.6
Classifier: Programming Language :: Python :: 3.7
Classifier: Programming Language :: Python :: 3.8
Classifier: Programming Language :: Python :: 3.9
Classifier: Programming Language :: Python :: 3.10
Classifier: Programming Language :: Python :: 3.11
Requires-Dist: aiofiles (>=23.2.1,<24.0.0)
Requires-Dist: anyio (>=4.1.0,<5.0.0)
Requires-Dist: black (>=23.12.0,<24.0.0)
Requires-Dist: dataclass-factory (>=2.16,<3.0)
Requires-Dist: di[anyio] (>=0.79.2,<0.80.0)
Requires-Dist: pytest (>=7.4.3,<8.0.0)
Requires-Dist: pytest-asyncio (>=0.23.2,<0.24.0)
